{
  "imdb_id": "tt2119373",
  "cast": null,
  "scene": null,
  "story": null,
  "cinematic_style": {
    "movie": null,
    "trailer": [
      {
        "shot": 1,
        "scale": "long",
        "movement": "static"
      },
      {
        "shot": 2,
        "scale": "long",
        "movement": "moving"
      },
      {
        "shot": 15,
        "scale": "full",
        "movement": "static"
      },
      {
        "shot": 22,
        "scale": "closeup",
        "movement": "static"
      },
      {
        "shot": 24,
        "scale": "closeup",
        "movement": "moving"
      },
      {
        "shot": 53,
        "scale": "long",
        "movement": "static"
      },
      {
        "shot": 55,
        "scale": "full",
        "movement": "moving"
      }
    ]
  }
}