{
  "imdb_id": "tt2291606",
  "cast": null,
  "scene": null,
  "story": null,
  "cinematic_style": {
    "movie": null,
    "trailer": [
      {
        "shot": 1,
        "scale": "long",
        "movement": "static"
      },
      {
        "shot": 9,
        "scale": "closeup",
        "movement": "static"
      },
      {
        "shot": 30,
        "scale": "long",
        "movement": "moving"
      },
      {
        "shot": 47,
        "scale": "closeup",
        "movement": "moving"
      },
      {
        "shot": 50,
        "scale": "full",
        "movement": "moving"
      }
    ]
  }
}