{
  "imdb_id": "tt3056608",
  "cast": null,
  "scene": null,
  "story": null,
  "cinematic_style": {
    "movie": null,
    "trailer": [
      {
        "shot": 12,
        "scale": "full",
        "movement": "moving"
      },
      {
        "shot": 16,
        "scale": "full",
        "movement": "pull"
      },
      {
        "shot": 38,
        "scale": "full",
        "movement": "moving"
      },
      {
        "shot": 62,
        "scale": "medium",
        "movement": "static"
      }
    ]
  }
}