{
  "imdb_id": "tt3053860",
  "cast": null,
  "scene": null,
  "story": null,
  "cinematic_style": {
    "movie": null,
    "trailer": [
      {
        "shot": 1,
        "scale": "medium",
        "movement": "static"
      },
      {
        "shot": 32,
        "scale": "closeup",
        "movement": "static"
      },
      {
        "shot": 43,
        "scale": "closeup",
        "movement": "static"
      },
      {
        "shot": 48,
        "scale": "closeup",
        "movement": "static"
      }
    ]
  }
}