{
  "imdb_id": "tt3238996",
  "cast": null,
  "scene": null,
  "story": null,
  "cinematic_style": {
    "movie": null,
    "trailer": [
      {
        "shot": 1,
        "scale": "closeup",
        "movement": "static"
      },
      {
        "shot": 6,
        "scale": "long",
        "movement": "static"
      },
      {
        "shot": 11,
        "scale": "full",
        "movement": "static"
      },
      {
        "shot": 31,
        "scale": "closeup",
        "movement": "static"
      },
      {
        "shot": 33,
        "scale": "medium",
        "movement": "static"
      },
      {
        "shot": 47,
        "scale": "closeup",
        "movement": "static"
      }
    ]
  }
}