{
  "imdb_id": "tt3586100",
  "cast": null,
  "scene": null,
  "story": null,
  "cinematic_style": {
    "movie": null,
    "trailer": [
      {
        "shot": 3,
        "scale": "medium",
        "movement": "static"
      },
      {
        "shot": 18,
        "scale": "closeup",
        "movement": "static"
      },
      {
        "shot": 32,
        "scale": "medium",
        "movement": "static"
      },
      {
        "shot": 33,
        "scale": "closeup",
        "movement": "static"
      },
      {
        "shot": 36,
        "scale": "long",
        "movement": "moving"
      },
      {
        "shot": 41,
        "scale": "medium",
        "movement": "static"
      },
      {
        "shot": 51,
        "scale": "closeup",
        "movement": "static"
      },
      {
        "shot": 54,
        "scale": "closeup",
        "movement": "static"
      },
      {
        "shot": 67,
        "scale": "full",
        "movement": "static"
      }
    ]
  }
}